bibtexautocomplete/__init__.py
bibtexautocomplete/__main__.py
bibtexautocomplete/APIs/__init__.py
bibtexautocomplete/APIs/arxiv.py
bibtexautocomplete/APIs/crossref.py
bibtexautocomplete/APIs/dblp.py
bibtexautocomplete/APIs/doi.py
bibtexautocomplete/APIs/inspire_hep.py
bibtexautocomplete/APIs/openalex.py
bibtexautocomplete/APIs/researchr.py
bibtexautocomplete/APIs/semantic_scholar.py
bibtexautocomplete/APIs/unpaywall.py
bibtexautocomplete/bibtex/__init__.py
bibtexautocomplete/bibtex/author.py
bibtexautocomplete/bibtex/base_field.py
bibtexautocomplete/bibtex/constants.py
bibtexautocomplete/bibtex/entry.py
bibtexautocomplete/bibtex/fields.py
bibtexautocomplete/bibtex/io.py
bibtexautocomplete/bibtex/normalize.py
bibtexautocomplete/core/__init__.py
bibtexautocomplete/core/apis.py
bibtexautocomplete/core/autocomplete.py
bibtexautocomplete/core/data_dump.py
bibtexautocomplete/core/main.py
bibtexautocomplete/core/parser.py
bibtexautocomplete/core/threads.py
bibtexautocomplete/lookups/__init__.py
bibtexautocomplete/lookups/abstract_base.py
bibtexautocomplete/lookups/abstract_entry_lookup.py
bibtexautocomplete/lookups/https.py
bibtexautocomplete/lookups/lookups.py
bibtexautocomplete/lookups/multiple_mixin.py
bibtexautocomplete/lookups/search_mixin.py
bibtexautocomplete/utils/__init__.py
bibtexautocomplete/utils/ansi.py
bibtexautocomplete/utils/constants.py
bibtexautocomplete/utils/functions.py
bibtexautocomplete/utils/logger.py
bibtexautocomplete/utils/only_exclude.py
bibtexautocomplete/utils/safe_json.py
bibtexautocomplete-1.4.3.dist-info/licenses/LICENSE
bibtexautocomplete-1.4.3.dist-info/METADATA
bibtexautocomplete-1.4.3.dist-info/WHEEL
bibtexautocomplete-1.4.3.dist-info/entry_points.txt
bibtexautocomplete-1.4.3.dist-info/top_level.txt
bibtexautocomplete-1.4.3.dist-info/RECORD
