Metadata-Version: 2.4
Name: bibtexautocomplete
Version: 1.4.3
Summary: Script to autocomplete bibtex files by polling online databases
Author-email: Dorian Lesbre <dorian.lesbre@gmail.com>
Maintainer-email: Dorian Lesbre <dorian.lesbre@gmail.com>
License: MIT License
Project-URL: Homepage, https://github.com/dlesbre/bibtex-autocomplete
Project-URL: Repository, https://github.com/dlesbre/bibtex-autocomplete.git
Project-URL: Issues, https://github.com/dlesbre/bibtex-autocomplete/issues
Project-URL: Changelog, https://github.com/dlesbre/bibtex-autocomplete/blob/master/CHANGELOG.md
Keywords: bibtex,biblatex,latex,autocomplete,btac
Classifier: Development Status :: 5 - Production/Stable
Classifier: Intended Audience :: Science/Research
Classifier: Intended Audience :: Developers
Classifier: Environment :: Console
Classifier: Natural Language :: English
Classifier: License :: OSI Approved :: MIT License
Classifier: Programming Language :: Python :: 3 :: Only
Classifier: Programming Language :: Python :: 3
Classifier: Programming Language :: Python :: 3.8
Classifier: Programming Language :: Python :: 3.9
Classifier: Programming Language :: Python :: 3.10
Classifier: Programming Language :: Python :: 3.11
Classifier: Programming Language :: Python :: 3.12
Classifier: Programming Language :: Python :: 3.13
Classifier: Operating System :: OS Independent
Classifier: Topic :: Text Processing :: Markup :: LaTeX
Classifier: Topic :: Internet :: WWW/HTTP :: Indexing/Search
Classifier: Topic :: Utilities
Classifier: Topic :: Scientific/Engineering
Classifier: Typing :: Typed
Requires-Python: >=3.8
License-File: LICENSE
Requires-Dist: bibtexparser<2.0.0
Requires-Dist: alive-progress>=3.0.0
Provides-Extra: tab
Requires-Dist: argcomplete; extra == "tab"
Provides-Extra: dev
Requires-Dist: argcomplete; extra == "dev"
Requires-Dist: pre-commit; extra == "dev"
Requires-Dist: pytest; extra == "dev"
Requires-Dist: pytest-stub; extra == "dev"
Requires-Dist: mypy; extra == "dev"
Requires-Dist: ruff; extra == "dev"
Requires-Dist: coverage; extra == "dev"
Requires-Dist: pytest-cov; extra == "dev"
Dynamic: license-file
